ucenter_sdk/__init__.py
ucenter_sdk/code_base.py
ucenter_sdk/commons.py
ucenter_sdk/config.py
ucenter_sdk/request_wraper.py
ucenter_sdk/ucenter_base.py
ucenter_sdk/ucenter_cas.py
ucenter_sdk/ucenter_info.py
ucenter_sdk/ucenter_oauth2.py
ucenter_sdk/ucenter_permission.py
ucenter_sdk/testing/__init__.py
ucenter_sdk/testing/flask_test.py
ucenter_sdk/testing/testing.py
ucenter_sdk/tools/__init__.py
ucenter_sdk/tools/cipher.py
ucenter_sdk/tools/popenapi.py
ucenter_sdk-1.0.13.dist-info/METADATA
ucenter_sdk-1.0.13.dist-info/WHEEL
ucenter_sdk-1.0.13.dist-info/top_level.txt
ucenter_sdk-1.0.13.dist-info/RECORD
