Metadata-Version: 2.1
Name: ucenter-sdk
Version: 1.0.13
Summary: YIDU UCenter SDK.
Home-page: UNKNOWN
Author: shiwei.ma
Author-email: shiwei.ma@yiducloud.cn
License: UNKNOWN
Keywords: user,ucenter
Platform: UNKNOWN
Requires-Dist: requests (>=2.11.1)
